Metadata-Version: 2.1
Name: errbot-feiyang
Version: 5.2.0
Summary: Errbot is a chatbot designed to be simple to extend with plugins written in Python.
Home-page: http://errbot.io/
Author: errbot.io
Author-email: info@errbot.io
License: GPL
Keywords: xmpp irc slack hipchat gitter tox chatbot bot plugin chatops
Platform: any
Classifier: Development Status :: 5 - Production/Stable
Classifier: Topic :: Communications :: Chat
Classifier: Topic :: Communications :: Chat :: Internet Relay Chat
Classifier: License :: OSI Approved :: GNU General Public License v3 (GPLv3)
Classifier: Operating System :: OS Independent
Classifier: Programming Language :: Python :: 3
Classifier: Programming Language :: Python :: 3.4
Classifier: Programming Language :: Python :: 3.5
Classifier: Programming Language :: Python :: 3.6
Requires-Dist: webtest
Requires-Dist: setuptools
Requires-Dist: bottle
Requires-Dist: rocket-errbot
Requires-Dist: requests
Requires-Dist: jinja2
Requires-Dist: pyOpenSSL
Requires-Dist: colorlog
Requires-Dist: yapsy (>=1.11)
Requires-Dist: markdown
Requires-Dist: ansi
Requires-Dist: Pygments (>=2.0.2)
Requires-Dist: pygments-markdown-lexer (>=0.1.0.dev39)
Requires-Dist: dnspython3
Requires-Dist: daemonize
Provides-Extra: irc
Requires-Dist: irc ; extra == 'irc'
Provides-Extra: xmpp
Requires-Dist: sleekxmpp ; extra == 'xmpp'
Requires-Dist: pyasn1 ; extra == 'xmpp'
Requires-Dist: pyasn1-modules ; extra == 'xmpp'
Provides-Extra: graphic
Requires-Dist: PySide ; extra == 'graphic'
Provides-Extra: hipchat
Requires-Dist: hypchat ; extra == 'hipchat'
Requires-Dist: sleekxmpp ; extra == 'hipchat'
Requires-Dist: pyasn1 ; extra == 'hipchat'
Requires-Dist: pyasn1-modules ; extra == 'hipchat'
Provides-Extra: slack
Requires-Dist: slackclient (>=1.0.5) ; extra == 'slack'
Provides-Extra: telegram
Requires-Dist: python-telegram-bot ; extra == 'telegram'
